wagtail_streamfield_migration_toolkit/__init__.py
wagtail_streamfield_migration_toolkit/apps.py
wagtail_streamfield_migration_toolkit/migrate_operation.py
wagtail_streamfield_migration_toolkit/models.py
wagtail_streamfield_migration_toolkit/operations.py
wagtail_streamfield_migration_toolkit/utils.py
wagtail_streamfield_migration_toolkit/wagtail_hooks.py
wagtail_streamfield_migration_toolkit/autodetect/comparers.py
wagtail_streamfield_migration_toolkit/autodetect/questioner.py
wagtail_streamfield_migration_toolkit/autodetect/streamchangedetector.py
wagtail_streamfield_migration_toolkit/management/__init__.py
wagtail_streamfield_migration_toolkit/management/commands/__init__.py
wagtail_streamfield_migration_toolkit/management/commands/streamchangedetect.py
wagtail_streamfield_migration_toolkit/management/commands/streamdatamigration.py
wagtail_streamfield_migration_toolkit/migrations/__init__.py
wagtail_streamfield_migration_toolkit/static/wagtail_streamfield_migration_toolkit/js/.gitignore
wagtail_streamfield_migration_toolkit/static_src/custom.d.ts
wagtail_streamfield_migration_toolkit/static_src/main.tsx
wagtail_streamfield_migration_toolkit/test/__init__.py
wagtail_streamfield_migration_toolkit/test/apps.py
wagtail_streamfield_migration_toolkit/test/factories.py
wagtail_streamfield_migration_toolkit/test/models.py
wagtail_streamfield_migration_toolkit/test/settings.py
wagtail_streamfield_migration_toolkit/test/testutils.py
wagtail_streamfield_migration_toolkit/test/urls.py
wagtail_streamfield_migration_toolkit/test/migrations/0001_initial.py
wagtail_streamfield_migration_toolkit/test/migrations/__init__.py
wagtail_streamfield_migration_toolkit/test/tests/__init__.py
wagtail_streamfield_migration_toolkit/test/tests/test_bad_data.py
wagtail_streamfield_migration_toolkit/test/tests/test_block_def_compare.py
wagtail_streamfield_migration_toolkit/test/tests/test_migration_names.py
wagtail_streamfield_migration_toolkit/test/tests/test_migrations.py
wagtail_streamfield_migration_toolkit-0.2.0.dist-info/LICENSE
wagtail_streamfield_migration_toolkit-0.2.0.dist-info/METADATA
wagtail_streamfield_migration_toolkit-0.2.0.dist-info/WHEEL
wagtail_streamfield_migration_toolkit-0.2.0.dist-info/top_level.txt
wagtail_streamfield_migration_toolkit-0.2.0.dist-info/RECORD
